self_llm/__init__.py
self_llm/engine.py
self_llm/model.py
self_llm/object.py
self_llm/utils.py
self_llm-0.0.5.dist-info/METADATA
self_llm-0.0.5.dist-info/WHEEL
self_llm-0.0.5.dist-info/licenses/LICENSE
self_llm-0.0.5.dist-info/RECORD
